LICENSE
Licence.txt
MANIFEST.in
README-en.md
README.md
requirements.txt
setup.cfg
setup.py
downloader/Config.py
downloader/ImageDownloadHelper.py
downloader/ImageDownloader.py
downloader/WebDriverManager.py
downloader/__init__.py
downloader/__main__.py
downloader/common/ImageParseResult.py
downloader/common/ImageResponse.py
downloader/common/__init__.py
downloader/engine/BaiduEngine.py
downloader/engine/BingEngine.py
downloader/engine/GoogleEngine.py
downloader/engine/SearchEngines.py
downloader/engine/__init__.py
image_downloader_ml.egg-info/PKG-INFO
image_downloader_ml.egg-info/SOURCES.txt
image_downloader_ml.egg-info/dependency_links.txt
image_downloader_ml.egg-info/entry_points.txt
image_downloader_ml.egg-info/requires.txt
image_downloader_ml.egg-info/top_level.txt