Metadata-Version: 2.1
Name: image-downloader-ml
Version: 1.0.9
Summary: Image download tools used in machine learning, deep learning.
Home-page: https://github.com/2635064692/image-downloader
Download-URL: https://github.com/2635064692/image-downloader/releases/download/1.0.9/image_downloader_ml-1.0.9.tar.gz
Author: Hai Zh
Author-email: peterzh1998@gmail.com
License: MIT
Keywords: google bing baidu images download image-dataset terminal command-line
Classifier: Development Status :: 4 - Beta
Classifier: Intended Audience :: Developers
Classifier: License :: OSI Approved :: MIT License
Classifier: Programming Language :: Python :: 2.7
Classifier: Programming Language :: Python :: 3.3
Classifier: Programming Language :: Python :: 3.4
Classifier: Programming Language :: Python :: 3.5
Classifier: Programming Language :: Python :: 3.6
License-File: LICENSE
License-File: Licence.txt
Requires-Dist: selenium~=4.24.0
Requires-Dist: webdriver_manager
Requires-Dist: setuptools~=75.1.0
Requires-Dist: requests~=2.32.3
Requires-Dist: pillow~=11.0.0
Requires-Dist: beautifulsoup4~=4.12.3
